DESCRIPTION.rst
MANIFEST.in
devprocess.py
setup.cfg
setup.py
devprocess.egg-info/PKG-INFO
devprocess.egg-info/SOURCES.txt
devprocess.egg-info/dependency_links.txt
devprocess.egg-info/entry_points.txt
devprocess.egg-info/requires.txt
devprocess.egg-info/top_level.txt