Metadata-Version: 1.1
Name: devprocess
Version: 0.9.5
Summary: JIRA Tools
Home-page: https://github.com/pypa/devprocess
Author: Akif Rahim
Author-email: akifrahim@gmail.com
License: UNKNOWN
Keywords: jira automation triage
Platform: UNKNOWN
Classifier: Development Status :: 3 - Alpha
Classifier: Intended Audience :: Developers
Classifier: Topic :: Utilities
Classifier: Programming Language :: Python :: 2.7
